table_token_generater_x21174105/__init__.py
table_token_generater_x21174105/token.py
table_token_generater_x21174105-0.0.1.dist-info/METADATA
table_token_generater_x21174105-0.0.1.dist-info/WHEEL
table_token_generater_x21174105-0.0.1.dist-info/licenses/LICENSE
table_token_generater_x21174105-0.0.1.dist-info/RECORD
