Metadata-Version: 2.1
Name: table_token_generater_x21174105
Version: 0.0.1
Summary: Table Token generator
Project-URL: Homepage, https://github.com/pypa/sampleproject
Project-URL: Bug Tracker, https://github.com/pypa/sampleproject/issues
Author-email: Nikhil Mondhe <nikhilmondhe46@gmail.com>
License-File: LICENSE
Classifier: License :: OSI Approved :: MIT License
Classifier: Operating System :: OS Independent
Classifier: Programming Language :: Python :: 3
Requires-Python: >=3.7
